libopensesametoolbox/__init__.py
libopensesametoolbox/clean_data.py
libopensesametoolbox/experimentmanager.py
libopensesametoolbox/experimentmanager_ui.py
libopensesametoolbox/io_tools.py
libopensesametoolbox/logger.py
libopensesametoolbox/questionnairecreator.py
libopensesametoolbox/questionnairecreator_ui.py
libopensesametoolbox/questionnaireprocessor.py
libopensesametoolbox/questionnaireprocessor_ui.py
opensesame_toolbox-2.8.data/data/share/applications/opensesame-experiment-manager.desktop
opensesame_toolbox-2.8.data/data/share/applications/opensesame-questionnaire-processor.desktop
opensesame_toolbox-2.8.data/data/share/icons/hicolor/scalable/apps/opensesame-toolbox.svg
opensesame_toolbox-2.8.data/data/share/mime/packages/x-opensesame-experiment-manager.xml
opensesame_toolbox-2.8.data/data/share/opensesametoolbox_resources/experimentmanager.icns
opensesame_toolbox-2.8.data/data/share/opensesametoolbox_resources/experimentmanager.ico
opensesame_toolbox-2.8.data/data/share/opensesametoolbox_resources/experimentmanager.png
opensesame_toolbox-2.8.data/data/share/opensesametoolbox_resources/experimentmanager.ui
opensesame_toolbox-2.8.data/data/share/opensesametoolbox_resources/help-about.png
opensesame_toolbox-2.8.data/data/share/opensesametoolbox_resources/help-contents.png
opensesame_toolbox-2.8.data/data/share/opensesametoolbox_resources/helpfile.html
opensesame_toolbox-2.8.data/data/share/opensesametoolbox_resources/opensesame-toolbox.conf
opensesame_toolbox-2.8.data/data/share/opensesametoolbox_resources/opensesame-toolbox.icns
opensesame_toolbox-2.8.data/data/share/opensesametoolbox_resources/opensesame-toolbox.ico
opensesame_toolbox-2.8.data/data/share/opensesametoolbox_resources/opensesame.script.mc
opensesame_toolbox-2.8.data/data/share/opensesametoolbox_resources/opensesame.script.open
opensesame_toolbox-2.8.data/data/share/opensesametoolbox_resources/questionnairecreator.ui
opensesame_toolbox-2.8.dist-info/COPYING
opensesame_toolbox-2.8.dist-info/METADATA
opensesame_toolbox-2.8.dist-info/WHEEL
opensesame_toolbox-2.8.dist-info/top_level.txt
opensesame_toolbox-2.8.dist-info/RECORD
