Metadata-Version: 2.1
Name: opensesame-toolbox
Version: 2.8
Summary: OpenSesame Toolbox can manage/execute all kinds of OpenSesame experiments. Additionally it can create and process scores from OpenSesame Questionnaires
Home-page: https://github.com/dev-jam/opensesame-toolbox
Author: Bob Rosbag
Author-email: debian@bobrosbag.nl
License: UNKNOWN
Platform: UNKNOWN
Classifier: Intended Audience :: Science/Research
Classifier: Topic :: Scientific/Engineering
Classifier: Environment :: Win32 (MS Windows)
Classifier: Environment :: X11 Applications
Classifier: License :: OSI Approved :: GNU General Public License v3 or later (GPLv3+)
Classifier: Programming Language :: Python :: 3
